etc/bash_completion.d/lolikit.bash-completion
lolikit/__init__.py
lolikit/app.py
lolikit/cmdline.py
lolikit/command.py
lolikit/defaultconfig.py
lolikit/info.py
lolikit/itemselector.py
lolikit/noteselector.py
lolikit/subcommandload.py
lolikit/utils.py
lolikit/servedata/mako/base.mako
lolikit/servedata/mako/directory.mako
lolikit/servedata/mako/frag_dir_bread.mako
lolikit/servedata/mako/frag_dir_content.mako
lolikit/servedata/mako/frag_navbar.mako
lolikit/servedata/mako/note.mako
lolikit/servedata/static/bootstrap/config.json
lolikit/servedata/static/bootstrap/css/bootstrap-theme.css
lolikit/servedata/static/bootstrap/css/bootstrap-theme.min.css
lolikit/servedata/static/bootstrap/css/bootstrap.css
lolikit/servedata/static/bootstrap/css/bootstrap.min.css
lolikit/servedata/static/bootstrap/fonts/glyphicons-halflings-regular.eot
lolikit/servedata/static/bootstrap/fonts/glyphicons-halflings-regular.svg
lolikit/servedata/static/bootstrap/fonts/glyphicons-halflings-regular.ttf
lolikit/servedata/static/bootstrap/fonts/glyphicons-halflings-regular.woff
lolikit/servedata/static/bootstrap/fonts/glyphicons-halflings-regular.woff2
lolikit/servedata/static/bootstrap/js/bootstrap.js
lolikit/servedata/static/bootstrap/js/bootstrap.min.js
lolikit/servedata/static/jquery/jquery-2.2.3.min.js
lolikit/servedata/static/lolinote/lolinote.css
lolikit/subcommands/__init__.py
lolikit/subcommands/check.py
lolikit/subcommands/config.py
lolikit/subcommands/do.py
lolikit/subcommands/find.py
lolikit/subcommands/help.py
lolikit/subcommands/init.py
lolikit/subcommands/list.py
lolikit/subcommands/serve.py
lolikit/subcommands/show.py
lolikit-1.4.0.dist-info/DESCRIPTION.rst
lolikit-1.4.0.dist-info/METADATA
lolikit-1.4.0.dist-info/RECORD
lolikit-1.4.0.dist-info/WHEEL
lolikit-1.4.0.dist-info/entry_points.txt
lolikit-1.4.0.dist-info/metadata.json
lolikit-1.4.0.dist-info/top_level.txt
