Metadata-Version: 2.0
Name: lolikit
Version: 1.4.0
Summary: Lolinote supporting toolkit
Home-page: https://bitbucket.org/civalin/lolikit
Author: Civa Lin
Author-email: larinawf@gmail.com
License: MIT
Keywords: notes-manager
Platform: UNKNOWN
Classifier: Programming Language :: Python :: 3
Classifier: Programming Language :: Python :: 3.4
Classifier: Programming Language :: Python :: 3.5
Classifier: Environment :: Console
Requires-Dist: CommonMark (>=0.6.4)
Requires-Dist: Mako (>=1.0)
Requires-Dist: bottle (>=0.12.0)
Requires-Dist: termcolor (>=1.1.0)
